cli.py
motif-images/x0.png
motif-images/x1.png
motif-images/x2.png
motif-images/x3.png
motif-images/x4.png
motif-images/x5.png
motif-images/y0.png
motif-images/y1.png
motif-images/y2.png
motif-images/y3.png
motif-images/y4.png
motif-images/y5.png
raphtory-0.16.4.dist-info/METADATA
raphtory-0.16.4.dist-info/WHEEL
raphtory-0.16.4.dist-info/entry_points.txt
raphtory/__init__.py
raphtory/__init__.pyi
raphtory/_raphtory.cpython-314-darwin.so
raphtory/algorithms/__init__.pyi
raphtory/filter/__init__.pyi
raphtory/graph_gen/__init__.pyi
raphtory/graph_loader/__init__.pyi
raphtory/graphql/__init__.pyi
raphtory/iterables/__init__.pyi
raphtory/node_state/__init__.pyi
raphtory/nullmodels.py
raphtory/plottingutils.py
raphtory/py.typed
raphtory/typing.py
raphtory/vectors/__init__.pyi
raphtory-0.16.4.dist-info/RECORD
